my_jupyter_shared_drive/__init__.py
my_jupyter_shared_drive-0.2.2.data/data/share/jupyter/labextensions/@jupyter/my-shared-docprovider-extension/package.json
my_jupyter_shared_drive-0.2.2.data/data/share/jupyter/labextensions/@jupyter/my-shared-docprovider-extension/static/234.908b475522f8002e1bc3.js
my_jupyter_shared_drive-0.2.2.data/data/share/jupyter/labextensions/@jupyter/my-shared-docprovider-extension/static/349.4d3231291439005544e6.js
my_jupyter_shared_drive-0.2.2.data/data/share/jupyter/labextensions/@jupyter/my-shared-docprovider-extension/static/612.326405af444f6fd355d2.js
my_jupyter_shared_drive-0.2.2.data/data/share/jupyter/labextensions/@jupyter/my-shared-docprovider-extension/static/631.b30847c2ed2769e1f267.js
my_jupyter_shared_drive-0.2.2.data/data/share/jupyter/labextensions/@jupyter/my-shared-docprovider-extension/static/remoteEntry.8075d86d43b9019300d9.js
my_jupyter_shared_drive-0.2.2.data/data/share/jupyter/labextensions/@jupyter/my-shared-docprovider-extension/static/style.js
my_jupyter_shared_drive-0.2.2.data/data/share/jupyter/labextensions/@jupyter/my-shared-docprovider-extension/static/third-party-licenses.json
my_jupyter_shared_drive-0.2.2.data/data/share/jupyter/labextensions/@jupyter/my-shared-docprovider-extension/install.json
my_jupyter_shared_drive-0.2.2.dist-info/METADATA
my_jupyter_shared_drive-0.2.2.dist-info/WHEEL
my_jupyter_shared_drive-0.2.2.dist-info/licenses/LICENSE
my_jupyter_shared_drive-0.2.2.dist-info/RECORD
